IITB_SSO.py
IITB_SSO-1.0.0.dist-info/METADATA
IITB_SSO-1.0.0.dist-info/WHEEL
IITB_SSO-1.0.0.dist-info/top_level.txt
IITB_SSO-1.0.0.dist-info/RECORD
