Metadata-Version: 2.1
Name: IITB-SSO
Version: 1.0.0
Summary: Python package to integrate IIT Bomaby SSO login to your project
Home-page: https://github.com/NihalSargaiya9/IITB-SSO
Author: Nihal Sargaiya
Author-email: nihalsargaiya4@gmail.com
License: MIT
Platform: UNKNOWN
Classifier: Programming Language :: Python :: 3
Classifier: License :: OSI Approved :: MIT License
Classifier: Operating System :: OS Independent
Requires-Python: >=3.6
Requires-Dist: Flask (>=2.0.2)
Requires-Dist: python-dotenv (>=0.19.2)
Requires-Dist: requests (>=2.26.0)
Requires-Dist: setuptools (>=59.0.1)
Requires-Dist: Werkzeug (==2.0.2)
